metaproject/cli.py
metaproject/config.py
metaproject/template.py
metaproject/test.py
metaproject-0.0.1.dist-info/METADATA
metaproject-0.0.1.dist-info/WHEEL
metaproject-0.0.1.dist-info/entry_points.txt
metaproject-0.0.1.dist-info/top_level.txt
metaproject-0.0.1.dist-info/RECORD
