Metadata-Version: 2.1
Name: metaproject
Version: 0.0.1
Summary: Scaffod projects from metaproject templates.
License: MIT
Requires-Python: >=3.9
Requires-Dist: click (==8.1.3)
Requires-Dist: Jinja2 (==3.0.3)
Requires-Dist: dataclasses-json (==0.5.7)
